datastructures/__init__.py
datastructures/linear/CDLL.py
datastructures/linear/CSLL.py
datastructures/linear/DLL.py
datastructures/linear/QueueLL.py
datastructures/linear/SLL.py
datastructures/linear/StackLL.py
datastructures/linear/__init__.py
datastructures/nodes/DNode.py
datastructures/nodes/TNode.py
datastructures/nodes/__init__.py
datastructures/test/__init__.py
datastructures/test/tests.py
datastructures/trees/AVL.py
datastructures/trees/BST.py
datastructures/trees/__init__.py
datastructureslibharrishasnain-1.0.dist-info/METADATA
datastructureslibharrishasnain-1.0.dist-info/WHEEL
datastructureslibharrishasnain-1.0.dist-info/top_level.txt
datastructureslibharrishasnain-1.0.dist-info/RECORD
